test
zencorpora
