Metadata-Version: 2.1
Name: zen-corpora
Version: 0.1.2
Summary: corpus-level trie to store corpus efficiently and speed up sentence search
Home-page: https://github.com/box-key/zen-corpora
Author: Kei Nemoto
Author-email: kei.nemoto28@gmail.com
License: Apache 2.0
Keywords: text search,natural language understanding,beam search,recurrent neural network,language modeling
Platform: UNKNOWN
Classifier: Programming Language :: Python :: 3 :: Only
Classifier: Programming Language :: Python :: 3.7
Classifier: License :: OSI Approved :: Apache Software License
Classifier: Operating System :: OS Independent
Classifier: Topic :: Scientific/Engineering :: Artificial Intelligence
